[
  {
    "name": "Affitto/Mutuo",
    "type": "Utility"
  },
  {
    "name": "Bollette",
    "type": "Utility"
  },
  {
    "name": "Cibo/Alimentari",
    "type": "Food"
  },
  {
    "name": "Ristoranti/Bar",
    "type": "Food"
  },
  {
    "name": "Salute",
    "type": "Health"
  },
  {
    "name": "Cinema",
    "type": "Entertainment"
  },
  {
    "name": "Abbigliamento",
    "type": "Clothing"
  },
  {
    "name": "Carburante",
    "type": "Transportation"
  },
  {
    "name": "Internet",
    "type": "Utility"
  },
  {
    "name": "Telefono",
    "type": "Utility"
  },
  {
    "name": "Spesa",
    "type": "Food"
  },
  {
    "name": "Trasporti",
    "type": "Transportation"
  },
  {
    "name": "Assicurazioni",
    "type": "Utility"
  },
  {
    "name": "Viaggi & Vacanze",
    "type": "Travel"
  },
  {
    "name": "Regali",
    "type": "Gifts"
  },
  {
    "name": "Sport",
    "type": "Entertainment"
  },
  {
    "name": "Istruzione",
    "type": "Education"
  },
  {
    "name": "Animali domestici",
    "type": "Pets"
  },
  {
    "name": "Shopping",
    "type": "Miscellaneous"
  },
  {
    "name": "Bambini",
    "type": "Family"
  },
  {
    "name": "Risparmi/investimenti",
    "type": "Savings"
  },
  {
    "name": "Spettacoli/eventi",
    "type": "Entertainment"
  },
  {
    "name": "Tasse",
    "type": "Utility"
  }
]
